siderunner/__init__.py
siderunner/__version__.py
siderunner/siderunner.py
siderunner-0.2.5.dist-info/LICENSE
siderunner-0.2.5.dist-info/METADATA
siderunner-0.2.5.dist-info/WHEEL
siderunner-0.2.5.dist-info/top_level.txt
siderunner-0.2.5.dist-info/RECORD
