Metadata-Version: 2.1
Name: siderunner
Version: 0.2.5
Summary: Runs Selenium IDE tests without Selenium IDE.
Home-page: https://github.com/dsilabs/siderunner
Author: Herb Lainchbury
Author-email: herb@dynamic-solutions.com
License: UNKNOWN
Platform: UNKNOWN
Classifier: Intended Audience :: Developers
Classifier: Topic :: Software Development :: Testing
Classifier: Programming Language :: Python :: 3
Classifier: License :: OSI Approved :: GNU General Public License v3 or later (GPLv3+)
Classifier: Operating System :: OS Independent
Requires-Dist: PyVirtualDisplay
Requires-Dist: selenium
